{"name":"BnW","targets":[{"id":"BnW-A-1","items":[{"id":"BnW-A-1-0","shape":"Circle","geostack":["Circle","Ellipse","TwoDim"],"center":[18,50],"size":[26,26],"filled":true,"area":2123},{"id":"BnW-A-1-1","shape":"Circle","geostack":["Circle","Ellipse","TwoDim"],"center":[50,82],"size":[26,26],"filled":true,"area":2123},{"id":"BnW-A-1-2","shape":"Circle","geostack":["Circle","Ellipse","TwoDim"],"center":[50,18],"size":[26,26],"filled":true,"area":2123},{"id":"BnW-A-1-3","shape":"Circle","geostack":["Circle","Ellipse","TwoDim"],"center":[82,50],"size":[26,26],"filled":true,"area":2123},{"id":"BnW-A-1-4","shape":"Circle","geostack":["Circle","Ellipse","TwoDim"],"center":[82,82],"size":[26,26],"filled":true,"area":2123}],"svg":"<?xml version=\"1.0\" encoding=\"UTF-8\" standalone=\"no\"?>\r\n      <g id=\"BnW-A-1-0\" class=\"filled\" transform=\"translate(18 50)\">\n      <circle cx=\"0\" cy=\"0\" r=\"13\"/>\n    </g><g id=\"BnW-A-1-1\" class=\"filled\" transform=\"translate(50 82)\">\n      <circle cx=\"0\" cy=\"0\" r=\"13\"/>\n    </g><g id=\"BnW-A-1-2\" class=\"filled\" transform=\"translate(50 18)\">\n      <circle cx=\"0\" cy=\"0\" r=\"13\"/>\n    </g><g id=\"BnW-A-1-3\" class=\"filled\" transform=\"translate(82 50)\">\n      <circle cx=\"0\" cy=\"0\" r=\"13\"/>\n    </g><g id=\"BnW-A-1-4\" class=\"filled\" transform=\"translate(82 82)\">\n      <circle cx=\"0\" cy=\"0\" r=\"13\"/>\n    </g>"},{"id":"BnW-A-2","items":[{"id":"BnW-A-2-0","shape":"Circle","geostack":["Circle","Ellipse","TwoDim"],"center":[82,50],"size":[26,26],"filled":true,"area":2123},{"id":"BnW-A-2-1","shape":"Circle","geostack":["Circle","Ellipse","TwoDim"],"center":[18,50],"size":[26,26],"filled":true,"area":2123},{"id":"BnW-A-2-2","shape":"Circle","geostack":["Circle","Ellipse","TwoDim"],"center":[82,82],"size":[26,26],"filled":true,"area":2123},{"id":"BnW-A-2-3","shape":"Circle","geostack":["Circle","Ellipse","TwoDim"],"center":[50,50],"size":[26,26],"filled":true,"area":2123},{"id":"BnW-A-2-4","shape":"Circle","geostack":["Circle","Ellipse","TwoDim"],"center":[82,18],"size":[26,26],"filled":true,"area":2123}],"svg":"<?xml version=\"1.0\" encoding=\"UTF-8\" standalone=\"no\"?>\r\n      <g id=\"BnW-A-2-0\" class=\"filled\" transform=\"translate(82 50)\">\n      <circle cx=\"0\" cy=\"0\" r=\"13\"/>\n    </g><g id=\"BnW-A-2-1\" class=\"filled\" transform=\"translate(18 50)\">\n      <circle cx=\"0\" cy=\"0\" r=\"13\"/>\n    </g><g id=\"BnW-A-2-2\" class=\"filled\" transform=\"translate(82 82)\">\n      <circle cx=\"0\" cy=\"0\" r=\"13\"/>\n    </g><g id=\"BnW-A-2-3\" class=\"filled\" transform=\"translate(50 50)\">\n      <circle cx=\"0\" cy=\"0\" r=\"13\"/>\n    </g><g id=\"BnW-A-2-4\" class=\"filled\" transform=\"translate(82 18)\">\n      <circle cx=\"0\" cy=\"0\" r=\"13\"/>\n    </g>"},{"id":"BnW-A-3","items":[{"id":"BnW-A-3-0","shape":"Circle","geostack":["Circle","Ellipse","TwoDim"],"center":[18,82],"size":[26,26],"filled":true,"area":2123},{"id":"BnW-A-3-1","shape":"Circle","geostack":["Circle","Ellipse","TwoDim"],"center":[82,82],"size":[26,26],"filled":true,"area":2123},{"id":"BnW-A-3-2","shape":"Circle","geostack":["Circle","Ellipse","TwoDim"],"center":[82,18],"size":[26,26],"filled":true,"area":2123},{"id":"BnW-A-3-3","shape":"Circle","geostack":["Circle","Ellipse","TwoDim"],"center":[50,82],"size":[26,26],"filled":true,"area":2123},{"id":"BnW-A-3-4","shape":"Circle","geostack":["Circle","Ellipse","TwoDim"],"center":[18,18],"size":[26,26],"filled":true,"area":2123}],"svg":"<?xml version=\"1.0\" encoding=\"UTF-8\" standalone=\"no\"?>\r\n      <g id=\"BnW-A-3-0\" class=\"filled\" transform=\"translate(18 82)\">\n      <circle cx=\"0\" cy=\"0\" r=\"13\"/>\n    </g><g id=\"BnW-A-3-1\" class=\"filled\" transform=\"translate(82 82)\">\n      <circle cx=\"0\" cy=\"0\" r=\"13\"/>\n    </g><g id=\"BnW-A-3-2\" class=\"filled\" transform=\"translate(82 18)\">\n      <circle cx=\"0\" cy=\"0\" r=\"13\"/>\n    </g><g id=\"BnW-A-3-3\" class=\"filled\" transform=\"translate(50 82)\">\n      <circle cx=\"0\" cy=\"0\" r=\"13\"/>\n    </g><g id=\"BnW-A-3-4\" class=\"filled\" transform=\"translate(18 18)\">\n      <circle cx=\"0\" cy=\"0\" r=\"13\"/>\n    </g>"},{"id":"BnW-A-4","items":[{"id":"BnW-A-4-0","shape":"Circle","geostack":["Circle","Ellipse","TwoDim"],"center":[50,18],"size":[26,26],"filled":true,"area":2123},{"id":"BnW-A-4-1","shape":"Circle","geostack":["Circle","Ellipse","TwoDim"],"center":[18,50],"size":[26,26],"filled":true,"area":2123},{"id":"BnW-A-4-2","shape":"Circle","geostack":["Circle","Ellipse","TwoDim"],"center":[50,82],"size":[26,26],"filled":true,"area":2123},{"id":"BnW-A-4-3","shape":"Circle","geostack":["Circle","Ellipse","TwoDim"],"center":[82,18],"size":[26,26],"filled":true,"area":2123},{"id":"BnW-A-4-4","shape":"Circle","geostack":["Circle","Ellipse","TwoDim"],"center":[82,50],"size":[26,26],"filled":true,"area":2123}],"svg":"<?xml version=\"1.0\" encoding=\"UTF-8\" standalone=\"no\"?>\r\n      <g id=\"BnW-A-4-0\" class=\"filled\" transform=\"translate(50 18)\">\n      <circle cx=\"0\" cy=\"0\" r=\"13\"/>\n    </g><g id=\"BnW-A-4-1\" class=\"filled\" transform=\"translate(18 50)\">\n      <circle cx=\"0\" cy=\"0\" r=\"13\"/>\n    </g><g id=\"BnW-A-4-2\" class=\"filled\" transform=\"translate(50 82)\">\n      <circle cx=\"0\" cy=\"0\" r=\"13\"/>\n    </g><g id=\"BnW-A-4-3\" class=\"filled\" transform=\"translate(82 18)\">\n      <circle cx=\"0\" cy=\"0\" r=\"13\"/>\n    </g><g id=\"BnW-A-4-4\" class=\"filled\" transform=\"translate(82 50)\">\n      <circle cx=\"0\" cy=\"0\" r=\"13\"/>\n    </g>"},{"id":"BnW-A-5","items":[{"id":"BnW-A-5-0","shape":"Circle","geostack":["Circle","Ellipse","TwoDim"],"center":[50,82],"size":[26,26],"filled":true,"area":2123},{"id":"BnW-A-5-1","shape":"Circle","geostack":["Circle","Ellipse","TwoDim"],"center":[82,82],"size":[26,26],"filled":true,"area":2123},{"id":"BnW-A-5-2","shape":"Circle","geostack":["Circle","Ellipse","TwoDim"],"center":[18,50],"size":[26,26],"filled":true,"area":2123},{"id":"BnW-A-5-3","shape":"Circle","geostack":["Circle","Ellipse","TwoDim"],"center":[82,18],"size":[26,26],"filled":true,"area":2123},{"id":"BnW-A-5-4","shape":"Circle","geostack":["Circle","Ellipse","TwoDim"],"center":[18,82],"size":[26,26],"filled":true,"area":2123}],"svg":"<?xml version=\"1.0\" encoding=\"UTF-8\" standalone=\"no\"?>\r\n      <g id=\"BnW-A-5-0\" class=\"filled\" transform=\"translate(50 82)\">\n      <circle cx=\"0\" cy=\"0\" r=\"13\"/>\n    </g><g id=\"BnW-A-5-1\" class=\"filled\" transform=\"translate(82 82)\">\n      <circle cx=\"0\" cy=\"0\" r=\"13\"/>\n    </g><g id=\"BnW-A-5-2\" class=\"filled\" transform=\"translate(18 50)\">\n      <circle cx=\"0\" cy=\"0\" r=\"13\"/>\n    </g><g id=\"BnW-A-5-3\" class=\"filled\" transform=\"translate(82 18)\">\n      <circle cx=\"0\" cy=\"0\" r=\"13\"/>\n    </g><g id=\"BnW-A-5-4\" class=\"filled\" transform=\"translate(18 82)\">\n      <circle cx=\"0\" cy=\"0\" r=\"13\"/>\n    </g>"},{"id":"BnW-A-6","items":[{"id":"BnW-A-6-0","shape":"Circle","geostack":["Circle","Ellipse","TwoDim"],"center":[18,82],"size":[26,26],"filled":true,"area":2123},{"id":"BnW-A-6-1","shape":"Circle","geostack":["Circle","Ellipse","TwoDim"],"center":[82,82],"size":[26,26],"filled":true,"area":2123},{"id":"BnW-A-6-2","shape":"Circle","geostack":["Circle","Ellipse","TwoDim"],"center":[18,50],"size":[26,26],"filled":true,"area":2123},{"id":"BnW-A-6-3","shape":"Circle","geostack":["Circle","Ellipse","TwoDim"],"center":[50,50],"size":[26,26],"filled":true,"area":2123},{"id":"BnW-A-6-4","shape":"Circle","geostack":["Circle","Ellipse","TwoDim"],"center":[50,18],"size":[26,26],"filled":true,"area":2123}],"svg":"<?xml version=\"1.0\" encoding=\"UTF-8\" standalone=\"no\"?>\r\n      <g id=\"BnW-A-6-0\" class=\"filled\" transform=\"translate(18 82)\">\n      <circle cx=\"0\" cy=\"0\" r=\"13\"/>\n    </g><g id=\"BnW-A-6-1\" class=\"filled\" transform=\"translate(82 82)\">\n      <circle cx=\"0\" cy=\"0\" r=\"13\"/>\n    </g><g id=\"BnW-A-6-2\" class=\"filled\" transform=\"translate(18 50)\">\n      <circle cx=\"0\" cy=\"0\" r=\"13\"/>\n    </g><g id=\"BnW-A-6-3\" class=\"filled\" transform=\"translate(50 50)\">\n      <circle cx=\"0\" cy=\"0\" r=\"13\"/>\n    </g><g id=\"BnW-A-6-4\" class=\"filled\" transform=\"translate(50 18)\">\n      <circle cx=\"0\" cy=\"0\" r=\"13\"/>\n    </g>"},{"id":"BnW-A-7","items":[{"id":"BnW-A-7-0","shape":"Circle","geostack":["Circle","Ellipse","TwoDim"],"center":[18,82],"size":[26,26],"filled":true,"area":2123},{"id":"BnW-A-7-1","shape":"Circle","geostack":["Circle","Ellipse","TwoDim"],"center":[50,18],"size":[26,26],"filled":true,"area":2123},{"id":"BnW-A-7-2","shape":"Circle","geostack":["Circle","Ellipse","TwoDim"],"center":[50,82],"size":[26,26],"filled":true,"area":2123},{"id":"BnW-A-7-3","shape":"Circle","geostack":["Circle","Ellipse","TwoDim"],"center":[82,18],"size":[26,26],"filled":true,"area":2123},{"id":"BnW-A-7-4","shape":"Circle","geostack":["Circle","Ellipse","TwoDim"],"center":[18,50],"size":[26,26],"filled":true,"area":2123}],"svg":"<?xml version=\"1.0\" encoding=\"UTF-8\" standalone=\"no\"?>\r\n      <g id=\"BnW-A-7-0\" class=\"filled\" transform=\"translate(18 82)\">\n      <circle cx=\"0\" cy=\"0\" r=\"13\"/>\n    </g><g id=\"BnW-A-7-1\" class=\"filled\" transform=\"translate(50 18)\">\n      <circle cx=\"0\" cy=\"0\" r=\"13\"/>\n    </g><g id=\"BnW-A-7-2\" class=\"filled\" transform=\"translate(50 82)\">\n      <circle cx=\"0\" cy=\"0\" r=\"13\"/>\n    </g><g id=\"BnW-A-7-3\" class=\"filled\" transform=\"translate(82 18)\">\n      <circle cx=\"0\" cy=\"0\" r=\"13\"/>\n    </g><g id=\"BnW-A-7-4\" class=\"filled\" transform=\"translate(18 50)\">\n      <circle cx=\"0\" cy=\"0\" r=\"13\"/>\n    </g>"},{"id":"BnW-A-8","items":[{"id":"BnW-A-8-0","shape":"Circle","geostack":["Circle","Ellipse","TwoDim"],"center":[18,50],"size":[26,26],"filled":true,"area":2123},{"id":"BnW-A-8-1","shape":"Circle","geostack":["Circle","Ellipse","TwoDim"],"center":[82,50],"size":[26,26],"filled":true,"area":2123},{"id":"BnW-A-8-2","shape":"Circle","geostack":["Circle","Ellipse","TwoDim"],"center":[18,82],"size":[26,26],"filled":true,"area":2123},{"id":"BnW-A-8-3","shape":"Circle","geostack":["Circle","Ellipse","TwoDim"],"center":[82,18],"size":[26,26],"filled":true,"area":2123},{"id":"BnW-A-8-4","shape":"Circle","geostack":["Circle","Ellipse","TwoDim"],"center":[50,50],"size":[26,26],"filled":true,"area":2123}],"svg":"<?xml version=\"1.0\" encoding=\"UTF-8\" standalone=\"no\"?>\r\n      <g id=\"BnW-A-8-0\" class=\"filled\" transform=\"translate(18 50)\">\n      <circle cx=\"0\" cy=\"0\" r=\"13\"/>\n    </g><g id=\"BnW-A-8-1\" class=\"filled\" transform=\"translate(82 50)\">\n      <circle cx=\"0\" cy=\"0\" r=\"13\"/>\n    </g><g id=\"BnW-A-8-2\" class=\"filled\" transform=\"translate(18 82)\">\n      <circle cx=\"0\" cy=\"0\" r=\"13\"/>\n    </g><g id=\"BnW-A-8-3\" class=\"filled\" transform=\"translate(82 18)\">\n      <circle cx=\"0\" cy=\"0\" r=\"13\"/>\n    </g><g id=\"BnW-A-8-4\" class=\"filled\" transform=\"translate(50 50)\">\n      <circle cx=\"0\" cy=\"0\" r=\"13\"/>\n    </g>"},{"id":"BnW-A-9","items":[{"id":"BnW-A-9-0","shape":"Circle","geostack":["Circle","Ellipse","TwoDim"],"center":[82,82],"size":[26,26],"filled":true,"area":2123},{"id":"BnW-A-9-1","shape":"Circle","geostack":["Circle","Ellipse","TwoDim"],"center":[82,18],"size":[26,26],"filled":true,"area":2123},{"id":"BnW-A-9-2","shape":"Circle","geostack":["Circle","Ellipse","TwoDim"],"center":[18,18],"size":[26,26],"filled":true,"area":2123},{"id":"BnW-A-9-3","shape":"Circle","geostack":["Circle","Ellipse","TwoDim"],"center":[18,50],"size":[26,26],"filled":true,"area":2123},{"id":"BnW-A-9-4","shape":"Circle","geostack":["Circle","Ellipse","TwoDim"],"center":[18,82],"size":[26,26],"filled":true,"area":2123}],"svg":"<?xml version=\"1.0\" encoding=\"UTF-8\" standalone=\"no\"?>\r\n      <g id=\"BnW-A-9-0\" class=\"filled\" transform=\"translate(82 82)\">\n      <circle cx=\"0\" cy=\"0\" r=\"13\"/>\n    </g><g id=\"BnW-A-9-1\" class=\"filled\" transform=\"translate(82 18)\">\n      <circle cx=\"0\" cy=\"0\" r=\"13\"/>\n    </g><g id=\"BnW-A-9-2\" class=\"filled\" transform=\"translate(18 18)\">\n      <circle cx=\"0\" cy=\"0\" r=\"13\"/>\n    </g><g id=\"BnW-A-9-3\" class=\"filled\" transform=\"translate(18 50)\">\n      <circle cx=\"0\" cy=\"0\" r=\"13\"/>\n    </g><g id=\"BnW-A-9-4\" class=\"filled\" transform=\"translate(18 82)\">\n      <circle cx=\"0\" cy=\"0\" r=\"13\"/>\n    </g>"},{"id":"BnW-A-10","items":[{"id":"BnW-A-10-0","shape":"Circle","geostack":["Circle","Ellipse","TwoDim"],"center":[50,82],"size":[26,26],"filled":true,"area":2123},{"id":"BnW-A-10-1","shape":"Circle","geostack":["Circle","Ellipse","TwoDim"],"center":[82,50],"size":[26,26],"filled":true,"area":2123},{"id":"BnW-A-10-2","shape":"Circle","geostack":["Circle","Ellipse","TwoDim"],"center":[50,18],"size":[26,26],"filled":true,"area":2123},{"id":"BnW-A-10-3","shape":"Circle","geostack":["Circle","Ellipse","TwoDim"],"center":[82,82],"size":[26,26],"filled":true,"area":2123},{"id":"BnW-A-10-4","shape":"Circle","geostack":["Circle","Ellipse","TwoDim"],"center":[18,18],"size":[26,26],"filled":true,"area":2123}],"svg":"<?xml version=\"1.0\" encoding=\"UTF-8\" standalone=\"no\"?>\r\n      <g id=\"BnW-A-10-0\" class=\"filled\" transform=\"translate(50 82)\">\n      <circle cx=\"0\" cy=\"0\" r=\"13\"/>\n    </g><g id=\"BnW-A-10-1\" class=\"filled\" transform=\"translate(82 50)\">\n      <circle cx=\"0\" cy=\"0\" r=\"13\"/>\n    </g><g id=\"BnW-A-10-2\" class=\"filled\" transform=\"translate(50 18)\">\n      <circle cx=\"0\" cy=\"0\" r=\"13\"/>\n    </g><g id=\"BnW-A-10-3\" class=\"filled\" transform=\"translate(82 82)\">\n      <circle cx=\"0\" cy=\"0\" r=\"13\"/>\n    </g><g id=\"BnW-A-10-4\" class=\"filled\" transform=\"translate(18 18)\">\n      <circle cx=\"0\" cy=\"0\" r=\"13\"/>\n    </g>"}],"counters":[{"id":"BnW-B-1","items":[{"id":"BnW-B-1-0","shape":"Circle","geostack":["Circle","Ellipse","TwoDim"],"center":[18,50],"size":[26,26],"filled":false,"area":2123},{"id":"BnW-B-1-1","shape":"Circle","geostack":["Circle","Ellipse","TwoDim"],"center":[82,18],"size":[26,26],"filled":false,"area":2123},{"id":"BnW-B-1-2","shape":"Circle","geostack":["Circle","Ellipse","TwoDim"],"center":[50,50],"size":[26,26],"filled":false,"area":2123},{"id":"BnW-B-1-3","shape":"Circle","geostack":["Circle","Ellipse","TwoDim"],"center":[18,82],"size":[26,26],"filled":false,"area":2123},{"id":"BnW-B-1-4","shape":"Circle","geostack":["Circle","Ellipse","TwoDim"],"center":[50,18],"size":[26,26],"filled":false,"area":2123}],"svg":"<?xml version=\"1.0\" encoding=\"UTF-8\" standalone=\"no\"?>\r\n      <g id=\"BnW-B-1-0\" class=\"empty\" transform=\"translate(18 50)\">\n      <circle cx=\"0\" cy=\"0\" r=\"13\"/>\n    </g><g id=\"BnW-B-1-1\" class=\"empty\" transform=\"translate(82 18)\">\n      <circle cx=\"0\" cy=\"0\" r=\"13\"/>\n    </g><g id=\"BnW-B-1-2\" class=\"empty\" transform=\"translate(50 50)\">\n      <circle cx=\"0\" cy=\"0\" r=\"13\"/>\n    </g><g id=\"BnW-B-1-3\" class=\"empty\" transform=\"translate(18 82)\">\n      <circle cx=\"0\" cy=\"0\" r=\"13\"/>\n    </g><g id=\"BnW-B-1-4\" class=\"empty\" transform=\"translate(50 18)\">\n      <circle cx=\"0\" cy=\"0\" r=\"13\"/>\n    </g>"},{"id":"BnW-B-2","items":[{"id":"BnW-B-2-0","shape":"Circle","geostack":["Circle","Ellipse","TwoDim"],"center":[50,18],"size":[26,26],"filled":false,"area":2123},{"id":"BnW-B-2-1","shape":"Circle","geostack":["Circle","Ellipse","TwoDim"],"center":[18,82],"size":[26,26],"filled":false,"area":2123},{"id":"BnW-B-2-2","shape":"Circle","geostack":["Circle","Ellipse","TwoDim"],"center":[82,82],"size":[26,26],"filled":false,"area":2123},{"id":"BnW-B-2-3","shape":"Circle","geostack":["Circle","Ellipse","TwoDim"],"center":[18,50],"size":[26,26],"filled":false,"area":2123},{"id":"BnW-B-2-4","shape":"Circle","geostack":["Circle","Ellipse","TwoDim"],"center":[82,50],"size":[26,26],"filled":false,"area":2123}],"svg":"<?xml version=\"1.0\" encoding=\"UTF-8\" standalone=\"no\"?>\r\n      <g id=\"BnW-B-2-0\" class=\"empty\" transform=\"translate(50 18)\">\n      <circle cx=\"0\" cy=\"0\" r=\"13\"/>\n    </g><g id=\"BnW-B-2-1\" class=\"empty\" transform=\"translate(18 82)\">\n      <circle cx=\"0\" cy=\"0\" r=\"13\"/>\n    </g><g id=\"BnW-B-2-2\" class=\"empty\" transform=\"translate(82 82)\">\n      <circle cx=\"0\" cy=\"0\" r=\"13\"/>\n    </g><g id=\"BnW-B-2-3\" class=\"empty\" transform=\"translate(18 50)\">\n      <circle cx=\"0\" cy=\"0\" r=\"13\"/>\n    </g><g id=\"BnW-B-2-4\" class=\"empty\" transform=\"translate(82 50)\">\n      <circle cx=\"0\" cy=\"0\" r=\"13\"/>\n    </g>"},{"id":"BnW-B-3","items":[{"id":"BnW-B-3-0","shape":"Circle","geostack":["Circle","Ellipse","TwoDim"],"center":[18,82],"size":[26,26],"filled":false,"area":2123},{"id":"BnW-B-3-1","shape":"Circle","geostack":["Circle","Ellipse","TwoDim"],"center":[82,50],"size":[26,26],"filled":false,"area":2123},{"id":"BnW-B-3-2","shape":"Circle","geostack":["Circle","Ellipse","TwoDim"],"center":[18,18],"size":[26,26],"filled":false,"area":2123},{"id":"BnW-B-3-3","shape":"Circle","geostack":["Circle","Ellipse","TwoDim"],"center":[18,50],"size":[26,26],"filled":false,"area":2123},{"id":"BnW-B-3-4","shape":"Circle","geostack":["Circle","Ellipse","TwoDim"],"center":[82,18],"size":[26,26],"filled":false,"area":2123}],"svg":"<?xml version=\"1.0\" encoding=\"UTF-8\" standalone=\"no\"?>\r\n      <g id=\"BnW-B-3-0\" class=\"empty\" transform=\"translate(18 82)\">\n      <circle cx=\"0\" cy=\"0\" r=\"13\"/>\n    </g><g id=\"BnW-B-3-1\" class=\"empty\" transform=\"translate(82 50)\">\n      <circle cx=\"0\" cy=\"0\" r=\"13\"/>\n    </g><g id=\"BnW-B-3-2\" class=\"empty\" transform=\"translate(18 18)\">\n      <circle cx=\"0\" cy=\"0\" r=\"13\"/>\n    </g><g id=\"BnW-B-3-3\" class=\"empty\" transform=\"translate(18 50)\">\n      <circle cx=\"0\" cy=\"0\" r=\"13\"/>\n    </g><g id=\"BnW-B-3-4\" class=\"empty\" transform=\"translate(82 18)\">\n      <circle cx=\"0\" cy=\"0\" r=\"13\"/>\n    </g>"},{"id":"BnW-B-4","items":[{"id":"BnW-B-4-0","shape":"Circle","geostack":["Circle","Ellipse","TwoDim"],"center":[82,82],"size":[26,26],"filled":false,"area":2123},{"id":"BnW-B-4-1","shape":"Circle","geostack":["Circle","Ellipse","TwoDim"],"center":[82,50],"size":[26,26],"filled":false,"area":2123},{"id":"BnW-B-4-2","shape":"Circle","geostack":["Circle","Ellipse","TwoDim"],"center":[50,50],"size":[26,26],"filled":false,"area":2123},{"id":"BnW-B-4-3","shape":"Circle","geostack":["Circle","Ellipse","TwoDim"],"center":[50,18],"size":[26,26],"filled":false,"area":2123},{"id":"BnW-B-4-4","shape":"Circle","geostack":["Circle","Ellipse","TwoDim"],"center":[18,50],"size":[26,26],"filled":false,"area":2123}],"svg":"<?xml version=\"1.0\" encoding=\"UTF-8\" standalone=\"no\"?>\r\n      <g id=\"BnW-B-4-0\" class=\"empty\" transform=\"translate(82 82)\">\n      <circle cx=\"0\" cy=\"0\" r=\"13\"/>\n    </g><g id=\"BnW-B-4-1\" class=\"empty\" transform=\"translate(82 50)\">\n      <circle cx=\"0\" cy=\"0\" r=\"13\"/>\n    </g><g id=\"BnW-B-4-2\" class=\"empty\" transform=\"translate(50 50)\">\n      <circle cx=\"0\" cy=\"0\" r=\"13\"/>\n    </g><g id=\"BnW-B-4-3\" class=\"empty\" transform=\"translate(50 18)\">\n      <circle cx=\"0\" cy=\"0\" r=\"13\"/>\n    </g><g id=\"BnW-B-4-4\" class=\"empty\" transform=\"translate(18 50)\">\n      <circle cx=\"0\" cy=\"0\" r=\"13\"/>\n    </g>"},{"id":"BnW-B-5","items":[{"id":"BnW-B-5-0","shape":"Circle","geostack":["Circle","Ellipse","TwoDim"],"center":[82,18],"size":[26,26],"filled":false,"area":2123},{"id":"BnW-B-5-1","shape":"Circle","geostack":["Circle","Ellipse","TwoDim"],"center":[50,18],"size":[26,26],"filled":false,"area":2123},{"id":"BnW-B-5-2","shape":"Circle","geostack":["Circle","Ellipse","TwoDim"],"center":[50,50],"size":[26,26],"filled":false,"area":2123},{"id":"BnW-B-5-3","shape":"Circle","geostack":["Circle","Ellipse","TwoDim"],"center":[82,50],"size":[26,26],"filled":false,"area":2123},{"id":"BnW-B-5-4","shape":"Circle","geostack":["Circle","Ellipse","TwoDim"],"center":[18,82],"size":[26,26],"filled":false,"area":2123}],"svg":"<?xml version=\"1.0\" encoding=\"UTF-8\" standalone=\"no\"?>\r\n      <g id=\"BnW-B-5-0\" class=\"empty\" transform=\"translate(82 18)\">\n      <circle cx=\"0\" cy=\"0\" r=\"13\"/>\n    </g><g id=\"BnW-B-5-1\" class=\"empty\" transform=\"translate(50 18)\">\n      <circle cx=\"0\" cy=\"0\" r=\"13\"/>\n    </g><g id=\"BnW-B-5-2\" class=\"empty\" transform=\"translate(50 50)\">\n      <circle cx=\"0\" cy=\"0\" r=\"13\"/>\n    </g><g id=\"BnW-B-5-3\" class=\"empty\" transform=\"translate(82 50)\">\n      <circle cx=\"0\" cy=\"0\" r=\"13\"/>\n    </g><g id=\"BnW-B-5-4\" class=\"empty\" transform=\"translate(18 82)\">\n      <circle cx=\"0\" cy=\"0\" r=\"13\"/>\n    </g>"},{"id":"BnW-B-6","items":[{"id":"BnW-B-6-0","shape":"Circle","geostack":["Circle","Ellipse","TwoDim"],"center":[82,50],"size":[26,26],"filled":false,"area":2123},{"id":"BnW-B-6-1","shape":"Circle","geostack":["Circle","Ellipse","TwoDim"],"center":[50,18],"size":[26,26],"filled":false,"area":2123},{"id":"BnW-B-6-2","shape":"Circle","geostack":["Circle","Ellipse","TwoDim"],"center":[18,18],"size":[26,26],"filled":false,"area":2123},{"id":"BnW-B-6-3","shape":"Circle","geostack":["Circle","Ellipse","TwoDim"],"center":[18,82],"size":[26,26],"filled":false,"area":2123},{"id":"BnW-B-6-4","shape":"Circle","geostack":["Circle","Ellipse","TwoDim"],"center":[82,18],"size":[26,26],"filled":false,"area":2123}],"svg":"<?xml version=\"1.0\" encoding=\"UTF-8\" standalone=\"no\"?>\r\n      <g id=\"BnW-B-6-0\" class=\"empty\" transform=\"translate(82 50)\">\n      <circle cx=\"0\" cy=\"0\" r=\"13\"/>\n    </g><g id=\"BnW-B-6-1\" class=\"empty\" transform=\"translate(50 18)\">\n      <circle cx=\"0\" cy=\"0\" r=\"13\"/>\n    </g><g id=\"BnW-B-6-2\" class=\"empty\" transform=\"translate(18 18)\">\n      <circle cx=\"0\" cy=\"0\" r=\"13\"/>\n    </g><g id=\"BnW-B-6-3\" class=\"empty\" transform=\"translate(18 82)\">\n      <circle cx=\"0\" cy=\"0\" r=\"13\"/>\n    </g><g id=\"BnW-B-6-4\" class=\"empty\" transform=\"translate(82 18)\">\n      <circle cx=\"0\" cy=\"0\" r=\"13\"/>\n    </g>"},{"id":"BnW-B-7","items":[{"id":"BnW-B-7-0","shape":"Circle","geostack":["Circle","Ellipse","TwoDim"],"center":[50,18],"size":[26,26],"filled":false,"area":2123},{"id":"BnW-B-7-1","shape":"Circle","geostack":["Circle","Ellipse","TwoDim"],"center":[18,50],"size":[26,26],"filled":false,"area":2123},{"id":"BnW-B-7-2","shape":"Circle","geostack":["Circle","Ellipse","TwoDim"],"center":[18,18],"size":[26,26],"filled":false,"area":2123},{"id":"BnW-B-7-3","shape":"Circle","geostack":["Circle","Ellipse","TwoDim"],"center":[82,18],"size":[26,26],"filled":false,"area":2123},{"id":"BnW-B-7-4","shape":"Circle","geostack":["Circle","Ellipse","TwoDim"],"center":[50,82],"size":[26,26],"filled":false,"area":2123}],"svg":"<?xml version=\"1.0\" encoding=\"UTF-8\" standalone=\"no\"?>\r\n      <g id=\"BnW-B-7-0\" class=\"empty\" transform=\"translate(50 18)\">\n      <circle cx=\"0\" cy=\"0\" r=\"13\"/>\n    </g><g id=\"BnW-B-7-1\" class=\"empty\" transform=\"translate(18 50)\">\n      <circle cx=\"0\" cy=\"0\" r=\"13\"/>\n    </g><g id=\"BnW-B-7-2\" class=\"empty\" transform=\"translate(18 18)\">\n      <circle cx=\"0\" cy=\"0\" r=\"13\"/>\n    </g><g id=\"BnW-B-7-3\" class=\"empty\" transform=\"translate(82 18)\">\n      <circle cx=\"0\" cy=\"0\" r=\"13\"/>\n    </g><g id=\"BnW-B-7-4\" class=\"empty\" transform=\"translate(50 82)\">\n      <circle cx=\"0\" cy=\"0\" r=\"13\"/>\n    </g>"},{"id":"BnW-B-8","items":[{"id":"BnW-B-8-0","shape":"Circle","geostack":["Circle","Ellipse","TwoDim"],"center":[18,82],"size":[26,26],"filled":false,"area":2123},{"id":"BnW-B-8-1","shape":"Circle","geostack":["Circle","Ellipse","TwoDim"],"center":[50,50],"size":[26,26],"filled":false,"area":2123},{"id":"BnW-B-8-2","shape":"Circle","geostack":["Circle","Ellipse","TwoDim"],"center":[82,18],"size":[26,26],"filled":false,"area":2123},{"id":"BnW-B-8-3","shape":"Circle","geostack":["Circle","Ellipse","TwoDim"],"center":[82,82],"size":[26,26],"filled":false,"area":2123},{"id":"BnW-B-8-4","shape":"Circle","geostack":["Circle","Ellipse","TwoDim"],"center":[18,18],"size":[26,26],"filled":false,"area":2123}],"svg":"<?xml version=\"1.0\" encoding=\"UTF-8\" standalone=\"no\"?>\r\n      <g id=\"BnW-B-8-0\" class=\"empty\" transform=\"translate(18 82)\">\n      <circle cx=\"0\" cy=\"0\" r=\"13\"/>\n    </g><g id=\"BnW-B-8-1\" class=\"empty\" transform=\"translate(50 50)\">\n      <circle cx=\"0\" cy=\"0\" r=\"13\"/>\n    </g><g id=\"BnW-B-8-2\" class=\"empty\" transform=\"translate(82 18)\">\n      <circle cx=\"0\" cy=\"0\" r=\"13\"/>\n    </g><g id=\"BnW-B-8-3\" class=\"empty\" transform=\"translate(82 82)\">\n      <circle cx=\"0\" cy=\"0\" r=\"13\"/>\n    </g><g id=\"BnW-B-8-4\" class=\"empty\" transform=\"translate(18 18)\">\n      <circle cx=\"0\" cy=\"0\" r=\"13\"/>\n    </g>"},{"id":"BnW-B-9","items":[{"id":"BnW-B-9-0","shape":"Circle","geostack":["Circle","Ellipse","TwoDim"],"center":[50,82],"size":[26,26],"filled":false,"area":2123},{"id":"BnW-B-9-1","shape":"Circle","geostack":["Circle","Ellipse","TwoDim"],"center":[18,50],"size":[26,26],"filled":false,"area":2123},{"id":"BnW-B-9-2","shape":"Circle","geostack":["Circle","Ellipse","TwoDim"],"center":[18,18],"size":[26,26],"filled":false,"area":2123},{"id":"BnW-B-9-3","shape":"Circle","geostack":["Circle","Ellipse","TwoDim"],"center":[50,50],"size":[26,26],"filled":false,"area":2123},{"id":"BnW-B-9-4","shape":"Circle","geostack":["Circle","Ellipse","TwoDim"],"center":[82,18],"size":[26,26],"filled":false,"area":2123}],"svg":"<?xml version=\"1.0\" encoding=\"UTF-8\" standalone=\"no\"?>\r\n      <g id=\"BnW-B-9-0\" class=\"empty\" transform=\"translate(50 82)\">\n      <circle cx=\"0\" cy=\"0\" r=\"13\"/>\n    </g><g id=\"BnW-B-9-1\" class=\"empty\" transform=\"translate(18 50)\">\n      <circle cx=\"0\" cy=\"0\" r=\"13\"/>\n    </g><g id=\"BnW-B-9-2\" class=\"empty\" transform=\"translate(18 18)\">\n      <circle cx=\"0\" cy=\"0\" r=\"13\"/>\n    </g><g id=\"BnW-B-9-3\" class=\"empty\" transform=\"translate(50 50)\">\n      <circle cx=\"0\" cy=\"0\" r=\"13\"/>\n    </g><g id=\"BnW-B-9-4\" class=\"empty\" transform=\"translate(82 18)\">\n      <circle cx=\"0\" cy=\"0\" r=\"13\"/>\n    </g>"},{"id":"BnW-B-10","items":[{"id":"BnW-B-10-0","shape":"Circle","geostack":["Circle","Ellipse","TwoDim"],"center":[82,50],"size":[26,26],"filled":false,"area":2123},{"id":"BnW-B-10-1","shape":"Circle","geostack":["Circle","Ellipse","TwoDim"],"center":[18,82],"size":[26,26],"filled":false,"area":2123},{"id":"BnW-B-10-2","shape":"Circle","geostack":["Circle","Ellipse","TwoDim"],"center":[50,18],"size":[26,26],"filled":false,"area":2123},{"id":"BnW-B-10-3","shape":"Circle","geostack":["Circle","Ellipse","TwoDim"],"center":[82,18],"size":[26,26],"filled":false,"area":2123},{"id":"BnW-B-10-4","shape":"Circle","geostack":["Circle","Ellipse","TwoDim"],"center":[50,82],"size":[26,26],"filled":false,"area":2123}],"svg":"<?xml version=\"1.0\" encoding=\"UTF-8\" standalone=\"no\"?>\r\n      <g id=\"BnW-B-10-0\" class=\"empty\" transform=\"translate(82 50)\">\n      <circle cx=\"0\" cy=\"0\" r=\"13\"/>\n    </g><g id=\"BnW-B-10-1\" class=\"empty\" transform=\"translate(18 82)\">\n      <circle cx=\"0\" cy=\"0\" r=\"13\"/>\n    </g><g id=\"BnW-B-10-2\" class=\"empty\" transform=\"translate(50 18)\">\n      <circle cx=\"0\" cy=\"0\" r=\"13\"/>\n    </g><g id=\"BnW-B-10-3\" class=\"empty\" transform=\"translate(82 18)\">\n      <circle cx=\"0\" cy=\"0\" r=\"13\"/>\n    </g><g id=\"BnW-B-10-4\" class=\"empty\" transform=\"translate(50 82)\">\n      <circle cx=\"0\" cy=\"0\" r=\"13\"/>\n    </g>"}],"tools":["expect","listLength","isFilled","every"]}